.clang-format
.flake8
.gitignore
.gitmodules
CHANGELOG.md
CODEOWNERS
CODE_OF_CONDUCT
Dockerfile
Dockerfile-cuda
Dockerfile-embedded
LICENSE
MANIFEST.in
Makefile
README.md
__init__.py
description.txt
packages.txt
setup.py
./src/opendr/__init__.py
./src/opendr/_setup.py
./src/opendr/_version.py
./src/opendr/control/__init__.py
./src/opendr/engine/__init__.py
./src/opendr/engine/constants.py
./src/opendr/engine/data.py
./src/opendr/engine/datasets.py
./src/opendr/engine/example_learner.py
./src/opendr/engine/learners.py
./src/opendr/engine/target.py
./src/opendr/perception/__init__.py
./src/opendr/perception/panoptic_segmentation/README.md
./src/opendr/perception/panoptic_segmentation/__init__.py
./src/opendr/perception/panoptic_segmentation/datasets/README.md
./src/opendr/perception/panoptic_segmentation/datasets/__init__.py
./src/opendr/perception/panoptic_segmentation/datasets/cityscapes.py
./src/opendr/perception/panoptic_segmentation/datasets/kitti.py
./src/opendr/perception/panoptic_segmentation/datasets/semantic_kitti.py
./src/opendr/perception/panoptic_segmentation/efficient_lps/__init__.py
./src/opendr/perception/panoptic_segmentation/efficient_lps/dependencies.ini
./src/opendr/perception/panoptic_segmentation/efficient_lps/efficient_lps_learner.py
./src/opendr/perception/panoptic_segmentation/efficient_lps/algorithm/__init__.py
./src/opendr/perception/panoptic_segmentation/efficient_lps/algorithm/EfficientLPS/.git
./src/opendr/perception/panoptic_segmentation/efficient_lps/algorithm/EfficientLPS/.gitignore
./src/opendr/perception/panoptic_segmentation/efficient_lps/algorithm/EfficientLPS/LICENSE
./src/opendr/perception/panoptic_segmentation/efficient_lps/algorithm/EfficientLPS/README.md
./src/opendr/perception/panoptic_segmentation/efficient_lps/algorithm/EfficientLPS/environment.yml
./src/opendr/perception/panoptic_segmentation/efficient_lps/algorithm/EfficientLPS/pytest.ini
./src/opendr/perception/panoptic_segmentation/efficient_lps/algorithm/EfficientLPS/efficientNet/geffnet.egg-info/PKG-INFO
./src/opendr/perception/panoptic_segmentation/efficient_lps/algorithm/EfficientLPS/efficientNet/geffnet.egg-info/SOURCES.txt
./src/opendr/perception/panoptic_segmentation/efficient_lps/algorithm/EfficientLPS/efficientNet/geffnet.egg-info/dependency_links.txt
./src/opendr/perception/panoptic_segmentation/efficient_lps/algorithm/EfficientLPS/efficientNet/geffnet.egg-info/requires.txt
./src/opendr/perception/panoptic_segmentation/efficient_lps/algorithm/EfficientLPS/efficientNet/geffnet.egg-info/top_level.txt
./src/opendr_toolkit_panoptic_segmentation.egg-info/PKG-INFO
./src/opendr_toolkit_panoptic_segmentation.egg-info/SOURCES.txt
./src/opendr_toolkit_panoptic_segmentation.egg-info/dependency_links.txt
./src/opendr_toolkit_panoptic_segmentation.egg-info/requires.txt
./src/opendr_toolkit_panoptic_segmentation.egg-info/top_level.txt
src/opendr/perception/panoptic_segmentation/efficient_lps/algorithm/EfficientLPS/efficientNet/geffnet.egg-info/PKG-INFO
src/opendr/perception/panoptic_segmentation/efficient_lps/algorithm/EfficientLPS/efficientNet/geffnet.egg-info/SOURCES.txt
src/opendr/perception/panoptic_segmentation/efficient_lps/algorithm/EfficientLPS/efficientNet/geffnet.egg-info/dependency_links.txt
src/opendr/perception/panoptic_segmentation/efficient_lps/algorithm/EfficientLPS/efficientNet/geffnet.egg-info/requires.txt
src/opendr/perception/panoptic_segmentation/efficient_lps/algorithm/EfficientLPS/efficientNet/geffnet.egg-info/top_level.txt
